[
    {
        "text": "\\o<span>文字列「」に最上位見出しを設定したい。適切なタグはどれか。",
        "choices": [
            "<p>情報科学専門学校</p>",
            "<h>情報科学専門学校</h>",
            "<m>情報科学専門学校</m>",
            "〇<h1>情報科学専門学校</h1>"
        ]
    },
    {
        "text": "meta要素の説明として正しいものはどれか。",
        "choices": [
            "文章のタイトルなど文章の補足情報を記載する",
            "HTML文章のタイトルを記載する",
            "最上位の要素である",
            "〇文字コードや文書の概要、キーワードなどブラウザ画面に表示されない文書情報を記載する"
        ]
    },
    {
        "text": "原稿から文書構造を読み取る際の視点として適切なものはどれか。",
        "choices": [
            "見出しを探す",
            "〇改行を探す",
            "箇条書きを探す",
            "文章のかたまりを探す"
        ]
    },
    {
        "text": "段落をつくる要素はどれか。",
        "choices": [
            "〇<p>文書文書・・・</p>",
            "<h>文書文書・・・</h>",
            "<m>文書文書・・・</m>",
            "<h1>文書文書・・・</h1>"
        ]
    },
    {
        "text": "HTMLの文書構造で正しい組み合わせはどれか。",
        "image": "Pic13.jpg",
        "choices": [
            "〇➀DOCTYPE宣言➁head要素➂body要素",
            "➀head要素➁body要素➂h要素",
            "➀body要素➁head要素➂h要素",
            "➀head要素➁DOCTYPE宣言➂body要素"
        ]
    }
]